asmc/preparedecoding/__init__.py
asmc/preparedecoding/decoding_quantities.py
asmc/preparedecoding/preparedecoding_python_bindings.cpython-313-x86_64-linux-gnu.so
include/ArraySpectrum.hpp
include/Csfs.hpp
include/CsfsEntry.hpp
include/Data.hpp
include/DecodingQuantities.hpp
include/DefaultArraySpectra.hpp
include/DefaultDemographies.hpp
include/EigenTypes.hpp
include/PrepareDecoding.hpp
include/ThinParameterTypes.hpp
include/Transition.hpp
include/Utils.hpp
lib64/libprepare_decoding_lib.a
lib64/libsmcpp_lib.a
lib64/cmake/AsmcPrepareDecoding/AsmcPrepareDecodingConfig.cmake
lib64/cmake/AsmcPrepareDecoding/AsmcPrepareDecoding_Runtime-release.cmake
lib64/cmake/AsmcPrepareDecoding/AsmcPrepareDecoding_Runtime.cmake
asmc_preparedecoding-2.2.5.dist-info/METADATA
asmc_preparedecoding-2.2.5.dist-info/WHEEL
asmc_preparedecoding-2.2.5.dist-info/RECORD
asmc_preparedecoding-2.2.5.dist-info/licenses/COPYING
asmc_preparedecoding-2.2.5.dist-info/licenses/LICENSE
